{"trueResult":{"probs":[0.1200721047798456,0.1200721047798456,0.048817674784679424,0.048817674784679334,0.1200721047798456,0.048817674784679334,0.011118950377064252,0.010715562362016269,0.2108482441872925,0.11571596985998082,0.046281546990427934,0.046281546990427934,0.02314368467239908,0.013717354480069664,0.008370657541954627,0.0071371438447920795],"support":["John is a doctor","John is a teacher","John is a doctor and a teacher","John is a doctor or a teacher","Mary is a doctor","Mary is a doctor or a teacher","Mary is not a teacher","Mary is not a doctor and a teacher","John and Mary are doctors","John and Mary are doctors or teachers","John or Mary is a doctor","John or Mary is a teacher","John or Mary is a doctor and a teacher","John or Mary is a doctor or a teacher","John or Mary is not a teacher","John or Mary is not a doctor and a teacher"]},"learnedResult":{"probs":[0.1200721047798456,0.1200721047798456,0.048817674784679424,0.048817674784679334,0.1200721047798456,0.048817674784679334,0.011118950377064252,0.010715562362016269,0.2108482441872925,0.11571596985998082,0.046281546990427934,0.046281546990427934,0.02314368467239908,0.013717354480069664,0.008370657541954627,0.0071371438447920795],"support":["John is a doctor","John is a teacher","John is a doctor and a teacher","John is a doctor or a teacher","Mary is a doctor","Mary is a doctor or a teacher","Mary is not a teacher","Mary is not a doctor and a teacher","John and Mary are doctors","John and Mary are doctors or teachers","John or Mary is a doctor","John or Mary is a teacher","John or Mary is a doctor and a teacher","John or Mary is a doctor or a teacher","John or Mary is not a teacher","John or Mary is not a doctor and a teacher"]},"KLDivergence":0}