{"trueResult":{"probs":[0.2932717129927225,0.3390202002709952,0.3390202002709952,0.028687886465286864],"support":[{"domain":["john","mary"],"facts":{"doctor":["john"],"teacher":["john"]}},{"domain":["john","mary"],"facts":{"doctor":["john"],"teacher":[]}},{"domain":["john","mary"],"facts":{"doctor":[],"teacher":["john"]}},{"domain":["john","mary"],"facts":{"doctor":[],"teacher":[]}}]},"learnedResult":{"probs":[0.00032111532810765196,0.006556709338096893,0.0008935574276469285,0.0076265799684157596,0.004832740047831634,0.22466370001676964,0.010043682079145943,0.2632028627255705,0.0008898686997149276,0.01357016770639611,0.0011735894911161725,0.010095012762454728,0.005610957883882818,0.2629379525052671,0.007464137295012174,0.18011736672457132],"support":[{"domain":["john","mary"],"facts":{"doctor":["john","mary"],"teacher":["john","mary"]}},{"domain":["john","mary"],"facts":{"doctor":["john","mary"],"teacher":["john"]}},{"domain":["john","mary"],"facts":{"doctor":["john","mary"],"teacher":["mary"]}},{"domain":["john","mary"],"facts":{"doctor":["john","mary"],"teacher":[]}},{"domain":["john","mary"],"facts":{"doctor":["john"],"teacher":["john","mary"]}},{"domain":["john","mary"],"facts":{"doctor":["john"],"teacher":["john"]}},{"domain":["john","mary"],"facts":{"doctor":["john"],"teacher":["mary"]}},{"domain":["john","mary"],"facts":{"doctor":["john"],"teacher":[]}},{"domain":["john","mary"],"facts":{"doctor":["mary"],"teacher":["john","mary"]}},{"domain":["john","mary"],"facts":{"doctor":["mary"],"teacher":["john"]}},{"domain":["john","mary"],"facts":{"doctor":["mary"],"teacher":["mary"]}},{"domain":["john","mary"],"facts":{"doctor":["mary"],"teacher":[]}},{"domain":["john","mary"],"facts":{"doctor":[],"teacher":["john","mary"]}},{"domain":["john","mary"],"facts":{"doctor":[],"teacher":["john"]}},{"domain":["john","mary"],"facts":{"doctor":[],"teacher":["mary"]}},{"domain":["john","mary"],"facts":{"doctor":[],"teacher":[]}}]},"KLDivergence":0.19742882384242863}